pw_database_url.py
setup.py
pw_database_url.egg-info/PKG-INFO
pw_database_url.egg-info/SOURCES.txt
pw_database_url.egg-info/dependency_links.txt
pw_database_url.egg-info/not-zip-safe
pw_database_url.egg-info/top_level.txt