Metadata-Version: 1.1
Name: pw-database-url
Version: 0.2.0
Summary: Use Database URLs in your Peewee ORM application.
Home-page: https://github.com/neilalbrock/pw-database-url
Author: Neil Albrock
Author-email: neil@atomised.coop
License: BSD
Platform: any
Classifier: Environment :: Web Environment
Classifier: Intended Audience :: Developers
Classifier: License :: OSI Approved :: BSD License
Classifier: Operating System :: OS Independent
Classifier: Programming Language :: Python
Classifier: Topic :: Internet :: WWW/HTTP :: Dynamic Content
Classifier: Topic :: Software Development :: Libraries :: Python Modules
